odoo/addons/delivery_dhl_parcel/README.rst
odoo/addons/delivery_dhl_parcel/__init__.py
odoo/addons/delivery_dhl_parcel/__manifest__.py
odoo/addons/delivery_dhl_parcel/doc/Documento_integracion_WEB_SERVICE_B2B_B2C_ver6.pdf
odoo/addons/delivery_dhl_parcel/i18n/ca.po
odoo/addons/delivery_dhl_parcel/i18n/delivery_dhl_parcel.pot
odoo/addons/delivery_dhl_parcel/i18n/es.po
odoo/addons/delivery_dhl_parcel/models/__init__.py
odoo/addons/delivery_dhl_parcel/models/delivery_carrier.py
odoo/addons/delivery_dhl_parcel/models/dhl_parcel_request.py
odoo/addons/delivery_dhl_parcel/models/sale_order.py
odoo/addons/delivery_dhl_parcel/models/stock_picking.py
odoo/addons/delivery_dhl_parcel/readme/CONFIGURE.md
odoo/addons/delivery_dhl_parcel/readme/CONTRIBUTORS.md
odoo/addons/delivery_dhl_parcel/readme/DESCRIPTION.md
odoo/addons/delivery_dhl_parcel/readme/INSTALL.md
odoo/addons/delivery_dhl_parcel/readme/ROADMAP.md
odoo/addons/delivery_dhl_parcel/readme/USAGE.md
odoo/addons/delivery_dhl_parcel/security/ir.model.access.csv
odoo/addons/delivery_dhl_parcel/static/description/icon.png
odoo/addons/delivery_dhl_parcel/static/description/index.html
odoo/addons/delivery_dhl_parcel/tests/__init__.py
odoo/addons/delivery_dhl_parcel/tests/test_delivery_dhl_parcel.py
odoo/addons/delivery_dhl_parcel/views/delivery_carrier_view.xml
odoo/addons/delivery_dhl_parcel/views/stock_picking_views.xml
odoo/addons/delivery_dhl_parcel/wizard/__init__.py
odoo/addons/delivery_dhl_parcel/wizard/dhl_parcel_end_day_wizard.py
odoo/addons/delivery_dhl_parcel/wizard/dhl_parcel_end_day_wizard_views.xml
odoo_addon_delivery_dhl_parcel-18.0.1.0.0.3.dist-info/METADATA
odoo_addon_delivery_dhl_parcel-18.0.1.0.0.3.dist-info/WHEEL
odoo_addon_delivery_dhl_parcel-18.0.1.0.0.3.dist-info/top_level.txt
odoo_addon_delivery_dhl_parcel-18.0.1.0.0.3.dist-info/RECORD
