Metadata-Version: 2.1
Name: odoo-addon-delivery_dhl_parcel
Version: 18.0.1.0.0.3
Requires-Python: >=3.10
Requires-Dist: odoo-addon-delivery_package_number==18.0.*
Requires-Dist: odoo-addon-delivery_state==18.0.*
Requires-Dist: odoo==18.0.*
Summary: Delivery Carrier implementation for DHL Parcel using their API
Home-page: https://github.com/OCA/l10n-spain
License: AGPL-3
Author: Studio73, Odoo Community Association (OCA)
Author-email: support@odoo-community.org
Classifier: Programming Language :: Python
Classifier: Framework :: Odoo
Classifier: Framework :: Odoo :: 18.0
Classifier: License :: OSI Approved :: GNU Affero General Public License v3
